{
	"item.modifier.blazified": "<gray><i>Блазифікований",
	"item.modifier.fragile": "<gray><i>Крихкий",
	"item.modifier.letter.friendship": [
		"<red><i>Містить силу дружби",
		"<!i><yellow><key:key.use><gray> по гравцю з пустою рукою,",
		"<!i><gray>щоб запропонувати дружбу"
	],
	"item.modifier.letter.friendship.bound": "<gray><!i>Дружня пропозиція від <from> для <to>",
	"item.modifier.letter.friendship.bound.you": [
		"<gray><!i>Дружня пропозиція від <from>",
		"<!i><yellow><key:key.use><gray> по ним, щоб прийняти пропозицію! "
	],
	"limbo.welcome": "Гм, ще один?",
	"limbo.welcome.interacted": "Так-так, добре! Дотримуйтесь інструкцій на екрані!",
	"limbo.welcome.ignored": "Збираєтесь мене ось так ігнорувати, дійсно? Буквально на екрані є інструкції…",
	"limbo.free_letter_already_obtained": "Гей, Ви ще не використали попередній!",
	"friendship.limbo": "Ви здружились з <gold>мандрівним крамарем</gold>!",
	"friendship.player": "Ви здружились з <gold><player></gold>!",
	"break.light": "Тут занадто темно, щоб ламати блоки",
	"advancement.reward.exp": "<blue><exp> <plural:uk_ua:одиниця|одиниці|одиниць:'<exp_raw>'> досвіду",
	"advancement.reward.shearable_creepers": "<yellow>+ Здатність стригти незаряджених кріперів",
	"advancement.reward.pottery_sherds": "<green>+1 кожного гончарського черепка",
	"advancement.reward.smithing_templates": "<green>+1 кожного ковальського шаблону",
	"advancement.announcement.super_challenge": "Гравець <player> завершив надвипробування <advancement>",
	"advancement.announcement.torture": "Гравець <player> завершив виснажливе досягнення <advancement>",
	"advancement.announcement.super_torture": "Гравець <player> завершив надвиснажливе досягнення <advancement>",
	"advancement.announcement.cheat": "Гравець <player> накрутив досягнення <advancement>",
	"advancement.trophy": "<gray><!i>Трофей <player> за <advancement>",
	"preferences.preference.adv_helper": "Показувати помічник для досягнень",
	"ritual.picker": "Оберіть ритуал:",
	"ritual.required_instruments": "Серед інструментів повинні бути:",
	"ritual.instruments.rattle": "Брязкальце",
	"ritual.instruments.flute": "Флейта",
	"ritual.instruments.drum": "Барабан",
	"ritual.instruments.trumpet": "Труба",
	"ritual.instruments.any": "Будь-які не з перелічених",
	"ritual.failed": "<red>Ритуал не вдався!",
	"recipes.potion.extended": "<icon:trapped_newbie:info> Збільшує тривалість ефекту",
	"recipes.potion.upgraded": "<icon:trapped_newbie:info> Підсилює ефект",
	"item.modifier.halloween_candy": "<gradient:gold:dark_gray>Гелловінський смаколик",
	"item.modifier.goodie_bag": "<dark_gray>Важливо ділитись з друзями!",
	"item.modifier.goodie_bag.looter": "<gray>Мішечок гравця <player>",
	"attrition.too_high": "Ваш рівень одержимості занадто високий"
}
